{
  "properties": [
    {
      "property": "rotation",
      "type": "integer",
      "values": [
        "0",
        "1",
        "2",
        "3",
        "4",
        "5",
        "6",
        "7",
        "8",
        "9",
        "10",
        "11",
        "12",
        "13",
        "14",
        "15"
      ]
    },
    {
      "property": "waterlogged",
      "type": "boolean",
      "values": [
        "true",
        "false"
      ]
    }
  ],
  "blockstates": [
    {
      "values": [
        {
          "property": "rotation",
          "value": "0"
        },
        {
          "property": "waterlogged",
          "value": "true"
        }
      ],
      "imageid": "193084535"
    },
    {
      "values": [
        {
          "property": "rotation",
          "value": "0"
        },
        {
          "property": "waterlogged",
          "value": "false"
        }
      ],
      "imageid": "257074798"
    },
    {
      "values": [
        {
          "property": "rotation",
          "value": "1"
        },
        {
          "property": "waterlogged",
          "value": "true"
        }
      ],
      "imageid": "-803987818"
    },
    {
      "values": [
        {
          "property": "rotation",
          "value": "1"
        },
        {
          "property": "waterlogged",
          "value": "false"
        }
      ],
      "imageid": "-587397073"
    },
    {
      "values": [
        {
          "property": "rotation",
          "value": "2"
        },
        {
          "property": "waterlogged",
          "value": "true"
        }
      ],
      "imageid": "-1801060171"
    },
    {
      "values": [
        {
          "property": "rotation",
          "value": "2"
        },
        {
          "property": "waterlogged",
          "value": "false"
        }
      ],
      "imageid": "-1431868944"
    },
    {
      "values": [
        {
          "property": "rotation",
          "value": "3"
        },
        {
          "property": "waterlogged",
          "value": "true"
        }
      ],
      "imageid": "1496834772"
    },
    {
      "values": [
        {
          "property": "rotation",
          "value": "3"
        },
        {
          "property": "waterlogged",
          "value": "false"
        }
      ],
      "imageid": "2018626481"
    },
    {
      "values": [
        {
          "property": "rotation",
          "value": "4"
        },
        {
          "property": "waterlogged",
          "value": "true"
        }
      ],
      "imageid": "499762419"
    },
    {
      "values": [
        {
          "property": "rotation",
          "value": "4"
        },
        {
          "property": "waterlogged",
          "value": "false"
        }
      ],
      "imageid": "1174154610"
    },
    {
      "values": [
        {
          "property": "rotation",
          "value": "5"
        },
        {
          "property": "waterlogged",
          "value": "true"
        }
      ],
      "imageid": "-497309934"
    },
    {
      "values": [
        {
          "property": "rotation",
          "value": "5"
        },
        {
          "property": "waterlogged",
          "value": "false"
        }
      ],
      "imageid": "329682739"
    },
    {
      "values": [
        {
          "property": "rotation",
          "value": "6"
        },
        {
          "property": "waterlogged",
          "value": "true"
        }
      ],
      "imageid": "-1494382287"
    },
    {
      "values": [
        {
          "property": "rotation",
          "value": "6"
        },
        {
          "property": "waterlogged",
          "value": "false"
        }
      ],
      "imageid": "-514789132"
    },
    {
      "values": [
        {
          "property": "rotation",
          "value": "7"
        },
        {
          "property": "waterlogged",
          "value": "true"
        }
      ],
      "imageid": "1803512656"
    },
    {
      "values": [
        {
          "property": "rotation",
          "value": "7"
        },
        {
          "property": "waterlogged",
          "value": "false"
        }
      ],
      "imageid": "-1359261003"
    },
    {
      "values": [
        {
          "property": "rotation",
          "value": "8"
        },
        {
          "property": "waterlogged",
          "value": "true"
        }
      ],
      "imageid": "806440303"
    },
    {
      "values": [
        {
          "property": "rotation",
          "value": "8"
        },
        {
          "property": "waterlogged",
          "value": "false"
        }
      ],
      "imageid": "2091234422"
    },
    {
      "values": [
        {
          "property": "rotation",
          "value": "9"
        },
        {
          "property": "waterlogged",
          "value": "true"
        }
      ],
      "imageid": "-190632050"
    },
    {
      "values": [
        {
          "property": "rotation",
          "value": "9"
        },
        {
          "property": "waterlogged",
          "value": "false"
        }
      ],
      "imageid": "1246762551"
    },
    {
      "values": [
        {
          "property": "rotation",
          "value": "10"
        },
        {
          "property": "waterlogged",
          "value": "true"
        }
      ],
      "imageid": "2061241546"
    },
    {
      "values": [
        {
          "property": "rotation",
          "value": "10"
        },
        {
          "property": "waterlogged",
          "value": "false"
        }
      ],
      "imageid": "-1959600005"
    },
    {
      "values": [
        {
          "property": "rotation",
          "value": "11"
        },
        {
          "property": "waterlogged",
          "value": "true"
        }
      ],
      "imageid": "1064169193"
    },
    {
      "values": [
        {
          "property": "rotation",
          "value": "11"
        },
        {
          "property": "waterlogged",
          "value": "false"
        }
      ],
      "imageid": "1490895420"
    },
    {
      "values": [
        {
          "property": "rotation",
          "value": "12"
        },
        {
          "property": "waterlogged",
          "value": "true"
        }
      ],
      "imageid": "67096840"
    },
    {
      "values": [
        {
          "property": "rotation",
          "value": "12"
        },
        {
          "property": "waterlogged",
          "value": "false"
        }
      ],
      "imageid": "646423549"
    },
    {
      "values": [
        {
          "property": "rotation",
          "value": "13"
        },
        {
          "property": "waterlogged",
          "value": "true"
        }
      ],
      "imageid": "-929975513"
    },
    {
      "values": [
        {
          "property": "rotation",
          "value": "13"
        },
        {
          "property": "waterlogged",
          "value": "false"
        }
      ],
      "imageid": "-198048322"
    },
    {
      "values": [
        {
          "property": "rotation",
          "value": "14"
        },
        {
          "property": "waterlogged",
          "value": "true"
        }
      ],
      "imageid": "-1927047866"
    },
    {
      "values": [
        {
          "property": "rotation",
          "value": "14"
        },
        {
          "property": "waterlogged",
          "value": "false"
        }
      ],
      "imageid": "-1042520193"
    },
    {
      "values": [
        {
          "property": "rotation",
          "value": "15"
        },
        {
          "property": "waterlogged",
          "value": "true"
        }
      ],
      "imageid": "1370847077"
    },
    {
      "values": [
        {
          "property": "rotation",
          "value": "15"
        },
        {
          "property": "waterlogged",
          "value": "false"
        }
      ],
      "imageid": "-1886992064"
    }
  ]
}