{
  "properties": [
    {
      "property": "face",
      "type": "enum",
      "values": [
        "FLOOR",
        "WALL",
        "CEILING"
      ]
    },
    {
      "property": "facing",
      "type": "enum",
      "values": [
        "north",
        "south",
        "west",
        "east"
      ]
    },
    {
      "property": "powered",
      "type": "boolean",
      "values": [
        "true",
        "false"
      ]
    }
  ],
  "blockstates": [
    {
      "values": [
        {
          "property": "face",
          "value": "FLOOR"
        },
        {
          "property": "facing",
          "value": "north"
        },
        {
          "property": "powered",
          "value": "true"
        }
      ],
      "imageid": "-112666513"
    },
    {
      "values": [
        {
          "property": "face",
          "value": "FLOOR"
        },
        {
          "property": "facing",
          "value": "north"
        },
        {
          "property": "powered",
          "value": "false"
        }
      ],
      "imageid": "-1175422306"
    },
    {
      "values": [
        {
          "property": "face",
          "value": "FLOOR"
        },
        {
          "property": "facing",
          "value": "south"
        },
        {
          "property": "powered",
          "value": "true"
        }
      ],
      "imageid": "1960303783"
    },
    {
      "values": [
        {
          "property": "face",
          "value": "FLOOR"
        },
        {
          "property": "facing",
          "value": "south"
        },
        {
          "property": "powered",
          "value": "false"
        }
      ],
      "imageid": "-1337852570"
    },
    {
      "values": [
        {
          "property": "face",
          "value": "FLOOR"
        },
        {
          "property": "facing",
          "value": "west"
        },
        {
          "property": "powered",
          "value": "true"
        }
      ],
      "imageid": "933112863"
    },
    {
      "values": [
        {
          "property": "face",
          "value": "FLOOR"
        },
        {
          "property": "facing",
          "value": "west"
        },
        {
          "property": "powered",
          "value": "false"
        }
      ],
      "imageid": "1178967278"
    },
    {
      "values": [
        {
          "property": "face",
          "value": "FLOOR"
        },
        {
          "property": "facing",
          "value": "east"
        },
        {
          "property": "powered",
          "value": "true"
        }
      ],
      "imageid": "90511505"
    },
    {
      "values": [
        {
          "property": "face",
          "value": "FLOOR"
        },
        {
          "property": "facing",
          "value": "east"
        },
        {
          "property": "powered",
          "value": "false"
        }
      ],
      "imageid": "828128956"
    },
    {
      "values": [
        {
          "property": "face",
          "value": "WALL"
        },
        {
          "property": "facing",
          "value": "north"
        },
        {
          "property": "powered",
          "value": "true"
        }
      ],
      "imageid": "-1118146643"
    },
    {
      "values": [
        {
          "property": "face",
          "value": "WALL"
        },
        {
          "property": "facing",
          "value": "north"
        },
        {
          "property": "powered",
          "value": "false"
        }
      ],
      "imageid": "2014432032"
    },
    {
      "values": [
        {
          "property": "face",
          "value": "WALL"
        },
        {
          "property": "facing",
          "value": "south"
        },
        {
          "property": "powered",
          "value": "true"
        }
      ],
      "imageid": "954823653"
    },
    {
      "values": [
        {
          "property": "face",
          "value": "WALL"
        },
        {
          "property": "facing",
          "value": "south"
        },
        {
          "property": "powered",
          "value": "false"
        }
      ],
      "imageid": "1852001768"
    },
    {
      "values": [
        {
          "property": "face",
          "value": "WALL"
        },
        {
          "property": "facing",
          "value": "west"
        },
        {
          "property": "powered",
          "value": "true"
        }
      ],
      "imageid": "1870509345"
    },
    {
      "values": [
        {
          "property": "face",
          "value": "WALL"
        },
        {
          "property": "facing",
          "value": "west"
        },
        {
          "property": "powered",
          "value": "false"
        }
      ],
      "imageid": "173487148"
    },
    {
      "values": [
        {
          "property": "face",
          "value": "WALL"
        },
        {
          "property": "facing",
          "value": "east"
        },
        {
          "property": "powered",
          "value": "true"
        }
      ],
      "imageid": "1027907987"
    },
    {
      "values": [
        {
          "property": "face",
          "value": "WALL"
        },
        {
          "property": "facing",
          "value": "east"
        },
        {
          "property": "powered",
          "value": "false"
        }
      ],
      "imageid": "-177351174"
    },
    {
      "values": [
        {
          "property": "face",
          "value": "CEILING"
        },
        {
          "property": "facing",
          "value": "north"
        },
        {
          "property": "powered",
          "value": "true"
        }
      ],
      "imageid": "-1977524768"
    },
    {
      "values": [
        {
          "property": "face",
          "value": "CEILING"
        },
        {
          "property": "facing",
          "value": "north"
        },
        {
          "property": "powered",
          "value": "false"
        }
      ],
      "imageid": "1143513933"
    },
    {
      "values": [
        {
          "property": "face",
          "value": "CEILING"
        },
        {
          "property": "facing",
          "value": "south"
        },
        {
          "property": "powered",
          "value": "true"
        }
      ],
      "imageid": "95445528"
    },
    {
      "values": [
        {
          "property": "face",
          "value": "CEILING"
        },
        {
          "property": "facing",
          "value": "south"
        },
        {
          "property": "powered",
          "value": "false"
        }
      ],
      "imageid": "981083669"
    },
    {
      "values": [
        {
          "property": "face",
          "value": "CEILING"
        },
        {
          "property": "facing",
          "value": "west"
        },
        {
          "property": "powered",
          "value": "true"
        }
      ],
      "imageid": "1842787470"
    },
    {
      "values": [
        {
          "property": "face",
          "value": "CEILING"
        },
        {
          "property": "facing",
          "value": "west"
        },
        {
          "property": "powered",
          "value": "false"
        }
      ],
      "imageid": "-685890977"
    },
    {
      "values": [
        {
          "property": "face",
          "value": "CEILING"
        },
        {
          "property": "facing",
          "value": "east"
        },
        {
          "property": "powered",
          "value": "true"
        }
      ],
      "imageid": "1000186112"
    },
    {
      "values": [
        {
          "property": "face",
          "value": "CEILING"
        },
        {
          "property": "facing",
          "value": "east"
        },
        {
          "property": "powered",
          "value": "false"
        }
      ],
      "imageid": "-1036729299"
    }
  ]
}