{
  "branch": "minecolonies:technology",
  "costs": [
    {
      "type": "minecolonies:item_simple",
      "item": "minecolonies:blockminecoloniesrack",
      "quantity": 16
    }
  ],
  "effects": [
    {
      "id": "minecolonies:effects/minimumstockmultiplier",
      "level": 1
    }
  ],
  "icon": "minecraft:chest",
  "parentResearch": "minecolonies:technology/sieving",
  "requirements": [
    {
      "type": "minecolonies:building",
      "building": "minecolonies:miner",
      "level": 3
    }
  ],
  "researchLevel": 3,
  "subtitle": "com.minecolonies.research.technology.space.subtitle"
}