{
  "properties": [
    {
      "property": "enabled",
      "type": "boolean",
      "values": [
        "true",
        "false"
      ]
    },
    {
      "property": "facing",
      "type": "enum",
      "values": [
        "down",
        "north",
        "south",
        "west",
        "east"
      ]
    }
  ],
  "blockstates": [
    {
      "values": [
        {
          "property": "enabled",
          "value": "true"
        },
        {
          "property": "facing",
          "value": "down"
        }
      ],
      "imageid": "-509024900"
    },
    {
      "values": [
        {
          "property": "enabled",
          "value": "true"
        },
        {
          "property": "facing",
          "value": "north"
        }
      ],
      "imageid": "-43055683"
    },
    {
      "values": [
        {
          "property": "enabled",
          "value": "true"
        },
        {
          "property": "facing",
          "value": "south"
        }
      ],
      "imageid": "-38435195"
    },
    {
      "values": [
        {
          "property": "enabled",
          "value": "true"
        },
        {
          "property": "facing",
          "value": "west"
        }
      ],
      "imageid": "-508468599"
    },
    {
      "values": [
        {
          "property": "enabled",
          "value": "true"
        },
        {
          "property": "facing",
          "value": "east"
        }
      ],
      "imageid": "-509008681"
    },
    {
      "values": [
        {
          "property": "enabled",
          "value": "false"
        },
        {
          "property": "facing",
          "value": "down"
        }
      ],
      "imageid": "1576020697"
    },
    {
      "values": [
        {
          "property": "enabled",
          "value": "false"
        },
        {
          "property": "facing",
          "value": "north"
        }
      ],
      "imageid": "168848384"
    },
    {
      "values": [
        {
          "property": "enabled",
          "value": "false"
        },
        {
          "property": "facing",
          "value": "south"
        }
      ],
      "imageid": "173468872"
    },
    {
      "values": [
        {
          "property": "enabled",
          "value": "false"
        },
        {
          "property": "facing",
          "value": "west"
        }
      ],
      "imageid": "1576576998"
    },
    {
      "values": [
        {
          "property": "enabled",
          "value": "false"
        },
        {
          "property": "facing",
          "value": "east"
        }
      ],
      "imageid": "1576036916"
    }
  ]
}